bouncer_insight/__init__.py
bouncer_insight/client.py
bouncer_insight/anotherone/__init__.py
bouncer_insight/events/__init__.py
bouncer_insight/events/base.py
bouncer_insight/events/label.py
bouncer_insight/events/login_event.py
bouncer_insight/events/misc.py
bouncer_insight/events/payment_method_add_event.py
bouncer_insight/events/user_create_event.py
bouncer_insight/events/user_update_event.py
tests/__init__.py
bouncer_insight-0.0.4.dist-info/LICENSE
bouncer_insight-0.0.4.dist-info/METADATA
bouncer_insight-0.0.4.dist-info/WHEEL
bouncer_insight-0.0.4.dist-info/top_level.txt
bouncer_insight-0.0.4.dist-info/RECORD
