Metadata-Version: 2.1
Name: bouncer-insight
Version: 0.0.4
Summary: Thin Python library for interacting with Bouncer Insight
Home-page: https://getbouncer.com
Author: Bouncer Inc.
Author-email: support@getbouncer.com
License: UNKNOWN
Platform: UNKNOWN
Classifier: Programming Language :: Python
Classifier: Programming Language :: Python :: 2.7
Classifier: Programming Language :: Python :: 3
Classifier: Programming Language :: Python :: 3.7
Classifier: Intended Audience :: Developers
Classifier: Topic :: Software Development :: Libraries :: Python Modules
Requires-Python: >=2.7
Requires-Dist: requests (>=2.5.0)
Requires-Dist: urllib3 (>=1.20)
